pyinapp/__init__.py
pyinapp/appstore.py
pyinapp/errors.py
pyinapp/googleplay.py
pyinapp/purchase.py
pyinapp-0.1.5.dist-info/LICENSE
pyinapp-0.1.5.dist-info/METADATA
pyinapp-0.1.5.dist-info/WHEEL
pyinapp-0.1.5.dist-info/top_level.txt
pyinapp-0.1.5.dist-info/RECORD
