Metadata-Version: 1.0
Name: pyinapp
Version: 0.1.5
Summary: InApp purchase validation API wrappers
Home-page: https://github.com/keeprocking/pyinapp
Author: Ivan Mukhin
Author-email: muhin.ivan@gmail.com
License: MIT
Keywords: inapp store purchase googleplay appstore market
Platform: UNKNOWN
